flake8_qt_tr/__init__.py
flake8_qt_tr/checker.py
flake8_qt_tr-0.2.0.dist-info/LICENSE
flake8_qt_tr-0.2.0.dist-info/METADATA
flake8_qt_tr-0.2.0.dist-info/WHEEL
flake8_qt_tr-0.2.0.dist-info/entry_points.txt
flake8_qt_tr-0.2.0.dist-info/top_level.txt
flake8_qt_tr-0.2.0.dist-info/RECORD
