Metadata-Version: 2.1
Name: flake8-qt-tr
Version: 0.2.0
Summary: Flake8 extension for detecting incorrect QT translation
Author: ostr00000
License: MIT
Project-URL: Homepage, https://github.com/ostr00000/flake8-qt-tr
Keywords: flake8,qt,translation
Classifier: Development Status :: 4 - Beta
Classifier: Environment :: Console
Classifier: Framework :: Flake8
Classifier: Intended Audience :: Developers
Classifier: License :: OSI Approved :: MIT License
Classifier: Operating System :: OS Independent
Classifier: Programming Language :: Python
Classifier: Programming Language :: Python :: 3
Classifier: Programming Language :: Python :: 3.10
Classifier: Programming Language :: Python :: 3.11
Classifier: Programming Language :: Python :: 3.12
Classifier: Programming Language :: Python :: 3 :: Only
Classifier: Topic :: Software Development :: Internationalization
Classifier: Topic :: Software Development :: Libraries :: Python Modules
Classifier: Topic :: Software Development :: Quality Assurance
Requires-Python: >=3.10
License-File: LICENSE
Requires-Dist: flake8 >=6.0.0
Provides-Extra: all
Requires-Dist: flake8-qt-tr[test] ; extra == 'all'
Provides-Extra: test
Requires-Dist: pytest ; extra == 'test'
